tests/__init__.py
tests/analytic/__init__.py
tests/analytic/test_integration.py
tests/callback/__init__.py
tests/callback/test_integration.py
tests/category/__init__.py
tests/category/test_integration.py
tests/entity/__init__.py
tests/entity/test_integration.py
tests/live/__init__.py
tests/live/test_integration.py
tests/livestreaming/__init__.py
tests/livestreaming/test_integration.py
tests/storage/__init__.py
tests/storage/test_integration.py
tests/user/__init__.py
tests/user/test_integration.py
uiza/__init__.py
uiza/exceptions.py
uiza/api_resources/__init__.py
uiza/api_resources/analytic/__init__.py
uiza/api_resources/analytic/analytic.py
uiza/api_resources/base/__init__.py
uiza/api_resources/base/base.py
uiza/api_resources/base/connections.py
uiza/api_resources/callback/__init__.py
uiza/api_resources/callback/callback.py
uiza/api_resources/category/__init__.py
uiza/api_resources/category/category.py
uiza/api_resources/entity/__init__.py
uiza/api_resources/entity/entity.py
uiza/api_resources/live/__init__.py
uiza/api_resources/live/live.py
uiza/api_resources/livestreaming/__init__.py
uiza/api_resources/livestreaming/livestreaming.py
uiza/api_resources/storage/__init__.py
uiza/api_resources/storage/storage.py
uiza/api_resources/user/__init__.py
uiza/api_resources/user/user.py
uiza/settings/__init__.py
uiza/settings/config.py
uiza/utility/__init__.py
uiza/utility/utility.py
uiza-1.2.0.dist-info/LICENSE
uiza-1.2.0.dist-info/METADATA
uiza-1.2.0.dist-info/WHEEL
uiza-1.2.0.dist-info/top_level.txt
uiza-1.2.0.dist-info/RECORD
