Metadata-Version: 2.1
Name: uiza
Version: 1.2.0
Summary: Uiza SDK tool
Home-page: https://github.com/uizaio/api-wrapper-python
Author: Uiza
Author-email: developer@uiza.io
License: UNKNOWN
Platform: UNKNOWN
Classifier: Programming Language :: Python
Classifier: License :: OSI Approved :: MIT License
Classifier: Operating System :: OS Independent
